{
  "poolInfo": {
    "inputs": [
      {
        "internalType": "uint256",
        "name": "",
        "type": "uint256"
      }
    ],
    "name": "poolInfo",
    "outputs": [
      {
        "internalType": "uint256",
        "name": "totalStake",
        "type": "uint256"
      },
      {
        "internalType": "contract IERC20",
        "name": "lpToken",
        "type": "address"
      },
      {
        "internalType": "uint256",
        "name": "allocPoint",
        "type": "uint256"
      },
      {
        "internalType": "uint256",
        "name": "lastRewardTime",
        "type": "uint256"
      },
      {
        "internalType": "uint256",
        "name": "accVSPerStake",
        "type": "uint256"
      },
      {
        "internalType": "uint16",
        "name": "depositFeeBP",
        "type": "uint16"
      }
    ],
    "stateMutability": "view",
    "type": "function"
  }
}
