{
  "registeredTokens": {
    "constant": true,
    "inputs": [
      {
        "internalType": "uint256",
        "name": "",
        "type": "uint256"
      }
    ],
    "name": "registeredTokens",
    "outputs": [
      {
        "internalType": "address",
        "name": "",
        "type": "address"
      }
    ],
    "payable": false,
    "stateMutability": "view",
    "type": "function"
  },
  "kToken": {
    "constant": true,
    "inputs": [
      {
        "internalType": "address",
        "name": "_token",
        "type": "address"
      }
    ],
    "name": "kToken",
    "outputs": [
      {
        "internalType": "contract IKToken",
        "name": "",
        "type": "address"
      }
    ],
    "payable": false,
    "stateMutability": "view",
    "type": "function"
  },
  "tokenByIndex": {
    "inputs": [
      {
        "internalType": "uint256",
        "name": "",
        "type": "uint256"
      }
    ],
    "name": "tokenByIndex",
    "outputs": [
      {
        "internalType": "address",
        "name": "",
        "type": "address"
      }
    ],
    "stateMutability": "view",
    "type": "function"
  },
  "getAllMarkets": {
    "constant": true,
    "inputs": [],
    "name": "getAllMarkets",
    "outputs": [
      {
        "internalType": "contract CToken[]",
        "name": "",
        "type": "address[]"
      }
    ],
    "payable": false,
    "stateMutability": "view",
    "type": "function"
  },
  "balanceOfUnderlying": {
    "constant": false,
    "inputs": [
      {
        "internalType": "address",
        "name": "owner",
        "type": "address"
      }
    ],
    "name": "balanceOfUnderlying",
    "outputs": [
      {
        "internalType": "uint256",
        "name": "",
        "type": "uint256"
      }
    ],
    "payable": false,
    "stateMutability": "nonpayable",
    "type": "function"
  },
  "underlying": {
    "constant": true,
    "inputs": [],
    "name": "underlying",
    "outputs": [
      {
        "internalType": "address",
        "name": "",
        "type": "address"
      }
    ],
    "payable": false,
    "stateMutability": "view",
    "type": "function"
  }
}
