[
  {
    "inputs": [
      {
        "internalType": "address",
        "name": "_initialOwner",
        "type": "address"
      },
      {
        "internalType": "address",
        "name": "_treasury",
        "type": "address"
      },
      {
        "internalType": "address",
        "name": "_stable",
        "type": "address"
      },
      {
        "internalType": "address",
        "name": "_vault",
        "type": "address"
      },
      {
        "internalType": "address",
        "name": "_debtToken",
        "type": "address"
      }
    ],
    "stateMutability": "nonpayable",
    "type": "constructor"
  },
  {
    "inputs": [
      {
        "internalType": "address",
        "name": "target",
        "type": "address"
      }
    ],
    "name": "AddressEmptyCode",
    "type": "error"
  },
  {
    "inputs": [
      {
        "internalType": "address",
        "name": "account",
        "type": "address"
      }
    ],
    "name": "AddressInsufficientBalance",
    "type": "error"
  },
  {
    "inputs": [],
    "name": "AlreadyInitialized",
    "type": "error"
  },
  {
    "inputs": [],
    "name": "AmountOutsideOfDeposit",
    "type": "error"
  },
  {
    "inputs": [],
    "name": "ClaimSuspended",
    "type": "error"
  },
  {
    "inputs": [],
    "name": "DepositSuspended",
    "type": "error"
  },
  {
    "inputs": [
      {
        "internalType": "address",
        "name": "spender",
        "type": "address"
      },
      {
        "internalType": "uint256",
        "name": "allowance",
        "type": "uint256"
      },
      {
        "internalType": "uint256",
        "name": "needed",
        "type": "uint256"
      }
    ],
    "name": "ERC20InsufficientAllowance",
    "type": "error"
  },
  {
    "inputs": [
      {
        "internalType": "address",
        "name": "sender",
        "type": "address"
      },
      {
        "internalType": "uint256",
        "name": "balance",
        "type": "uint256"
      },
      {
        "internalType": "uint256",
        "name": "needed",
        "type": "uint256"
      }
    ],
    "name": "ERC20InsufficientBalance",
    "type": "error"
  },
  {
    "inputs": [
      {
        "internalType": "address",
        "name": "approver",
        "type": "address"
      }
    ],
    "name": "ERC20InvalidApprover",
    "type": "error"
  },
  {
    "inputs": [
      {
        "internalType": "address",
        "name": "receiver",
        "type": "address"
      }
    ],
    "name": "ERC20InvalidReceiver",
    "type": "error"
  },
  {
    "inputs": [
      {
        "internalType": "address",
        "name": "sender",
        "type": "address"
      }
    ],
    "name": "ERC20InvalidSender",
    "type": "error"
  },
  {
    "inputs": [
      {
        "internalType": "address",
        "name": "spender",
        "type": "address"
      }
    ],
    "name": "ERC20InvalidSpender",
    "type": "error"
  },
  {
    "inputs": [],
    "name": "FailedInnerCall",
    "type": "error"
  },
  {
    "inputs": [],
    "name": "IdNotBelongsToUser",
    "type": "error"
  },
  {
    "inputs": [],
    "name": "InsufficientBalance",
    "type": "error"
  },
  {
    "inputs": [],
    "name": "LockedTimeNotPassed",
    "type": "error"
  },
  {
    "inputs": [],
    "name": "NoZeroAddress",
    "type": "error"
  },
  {
    "inputs": [],
    "name": "NoZeroAmount",
    "type": "error"
  },
  {
    "inputs": [
      {
        "internalType": "address",
        "name": "owner",
        "type": "address"
      }
    ],
    "name": "OwnableInvalidOwner",
    "type": "error"
  },
  {
    "inputs": [
      {
        "internalType": "address",
        "name": "account",
        "type": "address"
      }
    ],
    "name": "OwnableUnauthorizedAccount",
    "type": "error"
  },
  {
    "inputs": [],
    "name": "ReentrancyGuardReentrantCall",
    "type": "error"
  },
  {
    "inputs": [],
    "name": "RenounceOwnershipDisabled",
    "type": "error"
  },
  {
    "inputs": [
      {
        "internalType": "address",
        "name": "token",
        "type": "address"
      }
    ],
    "name": "SafeERC20FailedOperation",
    "type": "error"
  },
  {
    "anonymous": false,
    "inputs": [
      {
        "indexed": false,
        "internalType": "address",
        "name": "treasury",
        "type": "address"
      },
      {
        "indexed": false,
        "internalType": "address",
        "name": "stable",
        "type": "address"
      },
      {
        "indexed": false,
        "internalType": "address",
        "name": "vault",
        "type": "address"
      },
      {
        "indexed": false,
        "internalType": "address",
        "name": "debtToken",
        "type": "address"
      }
    ],
    "name": "AddressesSet",
    "type": "event"
  },
  {
    "anonymous": false,
    "inputs": [
      {
        "indexed": true,
        "internalType": "address",
        "name": "owner",
        "type": "address"
      },
      {
        "indexed": true,
        "internalType": "address",
        "name": "spender",
        "type": "address"
      },
      {
        "indexed": false,
        "internalType": "uint256",
        "name": "value",
        "type": "uint256"
      }
    ],
    "name": "Approval",
    "type": "event"
  },
  {
    "anonymous": false,
    "inputs": [
      {
        "indexed": true,
        "internalType": "address",
        "name": "user",
        "type": "address"
      },
      {
        "indexed": false,
        "internalType": "uint256",
        "name": "rewardAmount",
        "type": "uint256"
      }
    ],
    "name": "ClaimRewards",
    "type": "event"
  },
  {
    "anonymous": false,
    "inputs": [
      {
        "indexed": false,
        "internalType": "bool",
        "name": "status",
        "type": "bool"
      }
    ],
    "name": "ClaimStatusChanged",
    "type": "event"
  },
  {
    "anonymous": false,
    "inputs": [
      {
        "indexed": true,
        "internalType": "address",
        "name": "user",
        "type": "address"
      }
    ],
    "name": "DepositRemoved",
    "type": "event"
  },
  {
    "anonymous": false,
    "inputs": [
      {
        "indexed": false,
        "internalType": "bool",
        "name": "status",
        "type": "bool"
      }
    ],
    "name": "DepositStatusChanged",
    "type": "event"
  },
  {
    "anonymous": false,
    "inputs": [
      {
        "indexed": true,
        "internalType": "address",
        "name": "user",
        "type": "address"
      },
      {
        "indexed": false,
        "internalType": "uint256",
        "name": "amount",
        "type": "uint256"
      }
    ],
    "name": "Deposited",
    "type": "event"
  },
  {
    "anonymous": false,
    "inputs": [
      {
        "indexed": false,
        "internalType": "uint256",
        "name": "startDate",
        "type": "uint256"
      },
      {
        "indexed": false,
        "internalType": "uint256",
        "name": "endDate",
        "type": "uint256"
      },
      {
        "indexed": false,
        "internalType": "uint256",
        "name": "totalAllocation",
        "type": "uint256"
      },
      {
        "indexed": false,
        "internalType": "uint256",
        "name": "allocationPerSecond",
        "type": "uint256"
      }
    ],
    "name": "Initialized",
    "type": "event"
  },
  {
    "anonymous": false,
    "inputs": [
      {
        "indexed": true,
        "internalType": "address",
        "name": "previousOwner",
        "type": "address"
      },
      {
        "indexed": true,
        "internalType": "address",
        "name": "newOwner",
        "type": "address"
      }
    ],
    "name": "OwnershipTransferStarted",
    "type": "event"
  },
  {
    "anonymous": false,
    "inputs": [
      {
        "indexed": true,
        "internalType": "address",
        "name": "previousOwner",
        "type": "address"
      },
      {
        "indexed": true,
        "internalType": "address",
        "name": "newOwner",
        "type": "address"
      }
    ],
    "name": "OwnershipTransferred",
    "type": "event"
  },
  {
    "anonymous": false,
    "inputs": [
      {
        "indexed": true,
        "internalType": "address",
        "name": "user",
        "type": "address"
      },
      {
        "indexed": true,
        "internalType": "uint256",
        "name": "requestId",
        "type": "uint256"
      },
      {
        "indexed": false,
        "internalType": "uint256",
        "name": "amount",
        "type": "uint256"
      }
    ],
    "name": "Requested",
    "type": "event"
  },
  {
    "anonymous": false,
    "inputs": [
      {
        "indexed": true,
        "internalType": "address",
        "name": "from",
        "type": "address"
      },
      {
        "indexed": true,
        "internalType": "address",
        "name": "to",
        "type": "address"
      },
      {
        "indexed": false,
        "internalType": "uint256",
        "name": "value",
        "type": "uint256"
      }
    ],
    "name": "Transfer",
    "type": "event"
  },
  {
    "anonymous": false,
    "inputs": [
      {
        "indexed": false,
        "internalType": "address",
        "name": "trenToken",
        "type": "address"
      }
    ],
    "name": "TrenTokenSet",
    "type": "event"
  },
  {
    "anonymous": false,
    "inputs": [
      {
        "indexed": true,
        "internalType": "uint256",
        "name": "timestamp",
        "type": "uint256"
      },
      {
        "indexed": false,
        "internalType": "uint256",
        "name": "totalDepositedAmount",
        "type": "uint256"
      },
      {
        "indexed": false,
        "internalType": "uint256",
        "name": "rewardPerShare",
        "type": "uint256"
      }
    ],
    "name": "UpdatedRewardsPerShare",
    "type": "event"
  },
  {
    "anonymous": false,
    "inputs": [
      {
        "indexed": true,
        "internalType": "address",
        "name": "user",
        "type": "address"
      },
      {
        "indexed": true,
        "internalType": "uint256",
        "name": "id",
        "type": "uint256"
      },
      {
        "indexed": false,
        "internalType": "uint256",
        "name": "amount",
        "type": "uint256"
      }
    ],
    "name": "Withdrawn",
    "type": "event"
  },
  {
    "inputs": [],
    "name": "ACCUMULATED_PRECISION",
    "outputs": [
      {
        "internalType": "uint256",
        "name": "",
        "type": "uint256"
      }
    ],
    "stateMutability": "view",
    "type": "function"
  },
  {
    "inputs": [],
    "name": "acceptOwnership",
    "outputs": [],
    "stateMutability": "nonpayable",
    "type": "function"
  },
  {
    "inputs": [],
    "name": "allocationPerSecond",
    "outputs": [
      {
        "internalType": "uint256",
        "name": "",
        "type": "uint256"
      }
    ],
    "stateMutability": "view",
    "type": "function"
  },
  {
    "inputs": [
      {
        "internalType": "address",
        "name": "owner",
        "type": "address"
      },
      {
        "internalType": "address",
        "name": "spender",
        "type": "address"
      }
    ],
    "name": "allowance",
    "outputs": [
      {
        "internalType": "uint256",
        "name": "",
        "type": "uint256"
      }
    ],
    "stateMutability": "view",
    "type": "function"
  },
  {
    "inputs": [
      {
        "internalType": "address",
        "name": "spender",
        "type": "address"
      },
      {
        "internalType": "uint256",
        "name": "value",
        "type": "uint256"
      }
    ],
    "name": "approve",
    "outputs": [
      {
        "internalType": "bool",
        "name": "",
        "type": "bool"
      }
    ],
    "stateMutability": "nonpayable",
    "type": "function"
  },
  {
    "inputs": [
      {
        "internalType": "address",
        "name": "account",
        "type": "address"
      }
    ],
    "name": "balanceOf",
    "outputs": [
      {
        "internalType": "uint256",
        "name": "",
        "type": "uint256"
      }
    ],
    "stateMutability": "view",
    "type": "function"
  },
  {
    "inputs": [],
    "name": "claimRewards",
    "outputs": [],
    "stateMutability": "nonpayable",
    "type": "function"
  },
  {
    "inputs": [],
    "name": "claimSuspended",
    "outputs": [
      {
        "internalType": "bool",
        "name": "",
        "type": "bool"
      }
    ],
    "stateMutability": "view",
    "type": "function"
  },
  {
    "inputs": [],
    "name": "counter",
    "outputs": [
      {
        "internalType": "uint256",
        "name": "",
        "type": "uint256"
      }
    ],
    "stateMutability": "view",
    "type": "function"
  },
  {
    "inputs": [],
    "name": "currentAllocation",
    "outputs": [
      {
        "internalType": "uint256",
        "name": "",
        "type": "uint256"
      }
    ],
    "stateMutability": "view",
    "type": "function"
  },
  {
    "inputs": [],
    "name": "debtToken",
    "outputs": [
      {
        "internalType": "address",
        "name": "",
        "type": "address"
      }
    ],
    "stateMutability": "view",
    "type": "function"
  },
  {
    "inputs": [],
    "name": "decimals",
    "outputs": [
      {
        "internalType": "uint8",
        "name": "",
        "type": "uint8"
      }
    ],
    "stateMutability": "view",
    "type": "function"
  },
  {
    "inputs": [
      {
        "internalType": "uint256",
        "name": "amount",
        "type": "uint256"
      }
    ],
    "name": "deposit",
    "outputs": [],
    "stateMutability": "nonpayable",
    "type": "function"
  },
  {
    "inputs": [],
    "name": "depositSuspended",
    "outputs": [
      {
        "internalType": "bool",
        "name": "",
        "type": "bool"
      }
    ],
    "stateMutability": "view",
    "type": "function"
  },
  {
    "inputs": [],
    "name": "emergencyWithdraw",
    "outputs": [],
    "stateMutability": "nonpayable",
    "type": "function"
  },
  {
    "inputs": [],
    "name": "endDate",
    "outputs": [
      {
        "internalType": "uint256",
        "name": "",
        "type": "uint256"
      }
    ],
    "stateMutability": "view",
    "type": "function"
  },
  {
    "inputs": [
      {
        "internalType": "address",
        "name": "user",
        "type": "address"
      }
    ],
    "name": "getDepositData",
    "outputs": [
      {
        "components": [
          {
            "internalType": "uint256",
            "name": "depositedAmount",
            "type": "uint256"
          },
          {
            "internalType": "uint256",
            "name": "rewardDebt",
            "type": "uint256"
          },
          {
            "internalType": "uint256",
            "name": "pendingRewards",
            "type": "uint256"
          },
          {
            "internalType": "uint256",
            "name": "shares",
            "type": "uint256"
          },
          {
            "internalType": "uint256",
            "name": "amountToWithdraw",
            "type": "uint256"
          }
        ],
        "internalType": "struct ISingleLiquidityProvider.Deposit",
        "name": "",
        "type": "tuple"
      }
    ],
    "stateMutability": "view",
    "type": "function"
  },
  {
    "inputs": [
      {
        "internalType": "address",
        "name": "user",
        "type": "address"
      }
    ],
    "name": "getPendingRewards",
    "outputs": [
      {
        "internalType": "uint256",
        "name": "reward",
        "type": "uint256"
      }
    ],
    "stateMutability": "view",
    "type": "function"
  },
  {
    "inputs": [
      {
        "internalType": "uint256",
        "name": "requestId",
        "type": "uint256"
      }
    ],
    "name": "getRequestData",
    "outputs": [
      {
        "components": [
          {
            "internalType": "uint256",
            "name": "amountToWithdraw",
            "type": "uint256"
          },
          {
            "internalType": "uint256",
            "name": "unlockTimestamp",
            "type": "uint256"
          }
        ],
        "internalType": "struct ISingleLiquidityProvider.Request",
        "name": "",
        "type": "tuple"
      }
    ],
    "stateMutability": "view",
    "type": "function"
  },
  {
    "inputs": [],
    "name": "getRequestIds",
    "outputs": [
      {
        "internalType": "uint256[]",
        "name": "",
        "type": "uint256[]"
      }
    ],
    "stateMutability": "view",
    "type": "function"
  },
  {
    "inputs": [
      {
        "internalType": "address",
        "name": "user",
        "type": "address"
      }
    ],
    "name": "getUserRequestIds",
    "outputs": [
      {
        "internalType": "uint256[]",
        "name": "",
        "type": "uint256[]"
      }
    ],
    "stateMutability": "view",
    "type": "function"
  },
  {
    "inputs": [
      {
        "internalType": "uint256",
        "name": "allocation",
        "type": "uint256"
      }
    ],
    "name": "init",
    "outputs": [],
    "stateMutability": "nonpayable",
    "type": "function"
  },
  {
    "inputs": [],
    "name": "lastRewardBlockNumber",
    "outputs": [
      {
        "internalType": "uint256",
        "name": "",
        "type": "uint256"
      }
    ],
    "stateMutability": "view",
    "type": "function"
  },
  {
    "inputs": [],
    "name": "lastUpdatedTimestamp",
    "outputs": [
      {
        "internalType": "uint256",
        "name": "",
        "type": "uint256"
      }
    ],
    "stateMutability": "view",
    "type": "function"
  },
  {
    "inputs": [],
    "name": "name",
    "outputs": [
      {
        "internalType": "string",
        "name": "",
        "type": "string"
      }
    ],
    "stateMutability": "view",
    "type": "function"
  },
  {
    "inputs": [],
    "name": "owner",
    "outputs": [
      {
        "internalType": "address",
        "name": "",
        "type": "address"
      }
    ],
    "stateMutability": "view",
    "type": "function"
  },
  {
    "inputs": [],
    "name": "pendingOwner",
    "outputs": [
      {
        "internalType": "address",
        "name": "",
        "type": "address"
      }
    ],
    "stateMutability": "view",
    "type": "function"
  },
  {
    "inputs": [],
    "name": "renounceOwnership",
    "outputs": [],
    "stateMutability": "view",
    "type": "function"
  },
  {
    "inputs": [],
    "name": "rewardPerShare",
    "outputs": [
      {
        "internalType": "uint256",
        "name": "",
        "type": "uint256"
      }
    ],
    "stateMutability": "view",
    "type": "function"
  },
  {
    "inputs": [
      {
        "internalType": "address",
        "name": "_trenToken",
        "type": "address"
      }
    ],
    "name": "setTrenToken",
    "outputs": [],
    "stateMutability": "nonpayable",
    "type": "function"
  },
  {
    "inputs": [],
    "name": "stable",
    "outputs": [
      {
        "internalType": "contract IERC20Metadata",
        "name": "",
        "type": "address"
      }
    ],
    "stateMutability": "view",
    "type": "function"
  },
  {
    "inputs": [],
    "name": "switchClaimStatus",
    "outputs": [],
    "stateMutability": "nonpayable",
    "type": "function"
  },
  {
    "inputs": [],
    "name": "switchDepositStatus",
    "outputs": [],
    "stateMutability": "nonpayable",
    "type": "function"
  },
  {
    "inputs": [],
    "name": "symbol",
    "outputs": [
      {
        "internalType": "string",
        "name": "",
        "type": "string"
      }
    ],
    "stateMutability": "view",
    "type": "function"
  },
  {
    "inputs": [],
    "name": "totalAllocation",
    "outputs": [
      {
        "internalType": "uint256",
        "name": "",
        "type": "uint256"
      }
    ],
    "stateMutability": "view",
    "type": "function"
  },
  {
    "inputs": [],
    "name": "totalDepositedAmount",
    "outputs": [
      {
        "internalType": "uint256",
        "name": "",
        "type": "uint256"
      }
    ],
    "stateMutability": "view",
    "type": "function"
  },
  {
    "inputs": [],
    "name": "totalSupply",
    "outputs": [
      {
        "internalType": "uint256",
        "name": "",
        "type": "uint256"
      }
    ],
    "stateMutability": "view",
    "type": "function"
  },
  {
    "inputs": [
      {
        "internalType": "address",
        "name": "to",
        "type": "address"
      },
      {
        "internalType": "uint256",
        "name": "value",
        "type": "uint256"
      }
    ],
    "name": "transfer",
    "outputs": [
      {
        "internalType": "bool",
        "name": "",
        "type": "bool"
      }
    ],
    "stateMutability": "nonpayable",
    "type": "function"
  },
  {
    "inputs": [
      {
        "internalType": "address",
        "name": "from",
        "type": "address"
      },
      {
        "internalType": "address",
        "name": "to",
        "type": "address"
      },
      {
        "internalType": "uint256",
        "name": "value",
        "type": "uint256"
      }
    ],
    "name": "transferFrom",
    "outputs": [
      {
        "internalType": "bool",
        "name": "",
        "type": "bool"
      }
    ],
    "stateMutability": "nonpayable",
    "type": "function"
  },
  {
    "inputs": [
      {
        "internalType": "address",
        "name": "newOwner",
        "type": "address"
      }
    ],
    "name": "transferOwnership",
    "outputs": [],
    "stateMutability": "nonpayable",
    "type": "function"
  },
  {
    "inputs": [],
    "name": "treasury",
    "outputs": [
      {
        "internalType": "address",
        "name": "",
        "type": "address"
      }
    ],
    "stateMutability": "view",
    "type": "function"
  },
  {
    "inputs": [],
    "name": "trenToken",
    "outputs": [
      {
        "internalType": "contract IERC20Metadata",
        "name": "",
        "type": "address"
      }
    ],
    "stateMutability": "view",
    "type": "function"
  },
  {
    "inputs": [],
    "name": "updateRewardPerShare",
    "outputs": [],
    "stateMutability": "nonpayable",
    "type": "function"
  },
  {
    "inputs": [],
    "name": "vault",
    "outputs": [
      {
        "internalType": "contract IVault",
        "name": "",
        "type": "address"
      }
    ],
    "stateMutability": "view",
    "type": "function"
  },
  {
    "inputs": [
      {
        "internalType": "uint256",
        "name": "requestId",
        "type": "uint256"
      }
    ],
    "name": "withdraw",
    "outputs": [],
    "stateMutability": "nonpayable",
    "type": "function"
  },
  {
    "inputs": [
      {
        "internalType": "uint256",
        "name": "amount",
        "type": "uint256"
      }
    ],
    "name": "withdrawRequest",
    "outputs": [],
    "stateMutability": "nonpayable",
    "type": "function"
  }
]